{
  "2101145": {
    "name": "Kiến trúc máy tính",
    "range": {
      "A": 2,
      "A+": 1,
      "B": 4,
      "B+": 3,
      "C": 6,
      "C+": 5,
      "D": 8,
      "D+": 7,
      "F": 9
    }
  },
  "2101505": {
    "name": "Bảo mật hệ thống thông tin",
    "range": {
      "A": 11,
      "A+": 10,
      "B": 13,
      "B+": 12,
      "C": 15,
      "C+": 14,
      "D": 17,
      "D+": 16,
      "F": 18
    }
  },
  "2101508": {
    "name": "Hệ quản trị cơ sở dữ liệu",
    "range": {
      "A": 20,
      "A+": 19,
      "B": 22,
      "B+": 21,
      "C": 24,
      "C+": 23,
      "D": 26,
      "D+": 25,
      "F": 27
    }
  },
  "2101701": {
    "name": "Lập trình Windows",
    "range": {
      "A": 29,
      "A+": 28,
      "B": 31,
      "B+": 30,
      "C": 33,
      "C+": 32,
      "D": 35,
      "D+": 34,
      "F": 36
    }
  },
  "2101708": {
    "name": "Lập trình Java",
    "range": {
      "A": 38,
      "A+": 37,
      "B": 40,
      "B+": 39,
      "C": 42,
      "C+": 41,
      "D": 44,
      "D+": 43,
      "F": 45
    }
  },
  "2101710": {
    "name": "Lập trình Windows nâng cao",
    "range": {
      "A": 47,
      "A+": 46,
      "B": 49,
      "B+": 48,
      "C": 51,
      "C+": 50,
      "D": 53,
      "D+": 52,
      "F": 54
    }
  },
  "2101712": {
    "name": "Công nghệ thương mại điện tử",
    "range": {
      "A": 56,
      "A+": 55,
      "B": 58,
      "B+": 57,
      "C": 60,
      "C+": 59,
      "D": 62,
      "D+": 61,
      "F": 63
    }
  },
  "2101713": {
    "name": "Lập trình Java nâng cao",
    "range": {
      "A": 65,
      "A+": 64,
      "B": 67,
      "B+": 66,
      "C": 69,
      "C+": 68,
      "D": 71,
      "D+": 70,
      "F": 72
    }
  },
  "2101729": {
    "name": "Quản lý dự án CNTT",
    "range": {
      "A": 74,
      "A+": 73,
      "B": 76,
      "B+": 75,
      "C": 78,
      "C+": 77,
      "D": 80,
      "D+": 79,
      "F": 81
    }
  },
  "2101801": {
    "name": "Ngôn ngữ lập trình",
    "range": {
      "A": 83,
      "A+": 82,
      "B": 85,
      "B+": 84,
      "C": 87,
      "C+": 86,
      "D": 89,
      "D+": 88,
      "F": 90
    }
  },
  "2101802": {
    "name": "Cấu trúc rời rạc II",
    "range": {
      "A": 92,
      "A+": 91,
      "B": 94,
      "B+": 93,
      "C": 96,
      "C+": 95,
      "D": 98,
      "D+": 97,
      "F": 99
    }
  },
  "2101803": {
    "name": "Automat và ngôn ngữ hình thức",
    "range": {
      "A": 101,
      "A+": 100,
      "B": 103,
      "B+": 102,
      "C": 105,
      "C+": 104,
      "D": 107,
      "D+": 106,
      "F": 108
    }
  },
  "2101804": {
    "name": "Đồ họa máy tính",
    "range": {
      "A": 110,
      "A+": 109,
      "B": 112,
      "B+": 111,
      "C": 114,
      "C+": 113,
      "D": 116,
      "D+": 115,
      "F": 117
    }
  },
  "2101805": {
    "name": "Phân tích và thiết kế giải thuật",
    "range": {
      "A": 119,
      "A+": 118,
      "B": 121,
      "B+": 120,
      "C": 123,
      "C+": 122,
      "D": 125,
      "D+": 124,
      "F": 126
    }
  },
  "2101806": {
    "name": "Trí tuệ nhân tạo",
    "range": {
      "A": 128,
      "A+": 127,
      "B": 130,
      "B+": 129,
      "C": 132,
      "C+": 131,
      "D": 134,
      "D+": 133,
      "F": 135
    }
  },
  "2101808": {
    "name": "Xử lý ảnh",
    "range": {
      "A": 137,
      "A+": 136,
      "B": 139,
      "B+": 138,
      "C": 141,
      "C+": 140,
      "D": 143,
      "D+": 142,
      "F": 144
    }
  },
  "2101809": {
    "name": "Khai phá dữ liệu",
    "range": {
      "A": 146,
      "A+": 145,
      "B": 148,
      "B+": 147,
      "C": 150,
      "C+": 149,
      "D": 152,
      "D+": 151,
      "F": 153
    }
  },
  "2101810": {
    "name": "Xử lý ngôn ngữ tự nhiên",
    "range": {
      "A": 155,
      "A+": 154,
      "B": 157,
      "B+": 156,
      "C": 159,
      "C+": 158,
      "D": 161,
      "D+": 160,
      "F": 162
    }
  },
  "2101811": {
    "name": "Chương trình Dịch",
    "range": {
      "A": 164,
      "A+": 163,
      "B": 166,
      "B+": 165,
      "C": 168,
      "C+": 167,
      "D": 170,
      "D+": 169,
      "F": 171
    }
  },
  "2101908": {
    "name": "Phương pháp lập trình",
    "range": {
      "A": 173,
      "A+": 172,
      "B": 175,
      "B+": 174,
      "C": 177,
      "C+": 176,
      "D": 179,
      "D+": 178,
      "F": 180
    }
  },
  "2101909": {
    "name": "Kiến trúc máy tính",
    "range": {
      "A": 182,
      "A+": 181,
      "B": 184,
      "B+": 183,
      "C": 186,
      "C+": 185,
      "D": 188,
      "D+": 187,
      "F": 189
    }
  },
  "2101910": {
    "name": "Cấu trúc dữ liệu và giải thuật",
    "range": {
      "A": 191,
      "A+": 190,
      "B": 193,
      "B+": 192,
      "C": 195,
      "C+": 194,
      "D": 197,
      "D+": 196,
      "F": 198
    }
  },
  "2101911": {
    "name": "Tiếng Anh cho Tin học 1",
    "range": {
      "A": 200,
      "A+": 199,
      "B": 202,
      "B+": 201,
      "C": 204,
      "C+": 203,
      "D": 206,
      "D+": 205,
      "F": 207
    }
  },
  "2101912": {
    "name": "Tiếng Anh cho Tin học 2",
    "range": {
      "A": 209,
      "A+": 208,
      "B": 211,
      "B+": 210,
      "C": 213,
      "C+": 212,
      "D": 215,
      "D+": 214,
      "F": 216
    }
  },
  "2101913": {
    "name": "Hệ cơ sở dữ liệu",
    "range": {
      "A": 218,
      "A+": 217,
      "B": 220,
      "B+": 219,
      "C": 222,
      "C+": 221,
      "D": 224,
      "D+": 223,
      "F": 225
    }
  },
  "2101914": {
    "name": "Hệ điều hành",
    "range": {
      "A": 227,
      "A+": 226,
      "B": 229,
      "B+": 228,
      "C": 231,
      "C+": 230,
      "D": 233,
      "D+": 232,
      "F": 234
    }
  },
  "2101915": {
    "name": "Lập trình hướng đối tượng",
    "range": {
      "A": 236,
      "A+": 235,
      "B": 238,
      "B+": 237,
      "C": 240,
      "C+": 239,
      "D": 242,
      "D+": 241,
      "F": 243
    }
  },
  "2101916": {
    "name": "Mạng máy tính",
    "range": {
      "A": 245,
      "A+": 244,
      "B": 247,
      "B+": 246,
      "C": 249,
      "C+": 248,
      "D": 251,
      "D+": 250,
      "F": 252
    }
  },
  "2101917": {
    "name": "Công nghệ phần mềm",
    "range": {
      "A": 254,
      "A+": 253,
      "B": 256,
      "B+": 255,
      "C": 258,
      "C+": 257,
      "D": 260,
      "D+": 259,
      "F": 261
    }
  },
  "2101918": {
    "name": "Phân tích và thiết kế hệ thống",
    "range": {
      "A": 263,
      "A+": 262,
      "B": 265,
      "B+": 264,
      "C": 267,
      "C+": 266,
      "D": 269,
      "D+": 268,
      "F": 270
    }
  },
  "2101919": {
    "name": "Bài tập lớn học phần 1",
    "range": {
      "A": 272,
      "A+": 271,
      "B": 274,
      "B+": 273,
      "C": 276,
      "C+": 275,
      "D": 278,
      "D+": 277,
      "F": 279
    }
  },
  "2101920": {
    "name": "Bài tập lớn học phần 2",
    "range": {
      "A": 281,
      "A+": 280,
      "B": 283,
      "B+": 282,
      "C": 285,
      "C+": 284,
      "D": 287,
      "D+": 286,
      "F": 288
    }
  },
  "2101921": {
    "name": "Thực tập tốt nghiệp",
    "range": {
      "A": 290,
      "A+": 289,
      "B": 292,
      "B+": 291,
      "C": 294,
      "C+": 293,
      "D": 296,
      "D+": 295,
      "F": 297
    }
  },
  "2101923": {
    "name": "Đồ án chuyên ngành",
    "range": {
      "A": 299,
      "A+": 298,
      "B": 301,
      "B+": 300,
      "C": 303,
      "C+": 302,
      "D": 305,
      "D+": 304,
      "F": 306
    }
  },
  "2101924": {
    "name": "Nhập môn Tin học",
    "range": {
      "A": 308,
      "A+": 307,
      "B": 310,
      "B+": 309,
      "C": 312,
      "C+": 311,
      "D": 314,
      "D+": 313,
      "F": 315
    }
  },
  "2101925": {
    "name": "Cấu trúc rời rạc I",
    "range": {
      "A": 317,
      "A+": 316,
      "B": 319,
      "B+": 318,
      "C": 321,
      "C+": 320,
      "D": 323,
      "D+": 322,
      "F": 324
    }
  },
  "2113001": {
    "name": "Toán A1",
    "range": {
      "A": 326,
      "A+": 325,
      "B": 328,
      "B+": 327,
      "C": 330,
      "C+": 329,
      "D": 332,
      "D+": 331,
      "F": 333
    }
  },
  "2113002": {
    "name": "Toán A2",
    "range": {
      "A": 335,
      "A+": 334,
      "B": 337,
      "B+": 336,
      "C": 339,
      "C+": 338,
      "D": 341,
      "D+": 340,
      "F": 342
    }
  },
  "2113007": {
    "name": "Vật lí 1",
    "range": {
      "A": 344,
      "A+": 343,
      "B": 346,
      "B+": 345,
      "C": 348,
      "C+": 347,
      "D": 350,
      "D+": 349,
      "F": 351
    }
  },
  "2113008": {
    "name": "Vật lí 2",
    "range": {
      "A": 353,
      "A+": 352,
      "B": 355,
      "B+": 354,
      "C": 357,
      "C+": 356,
      "D": 359,
      "D+": 358,
      "F": 360
    }
  },
  "2113010": {
    "name": "Phương pháp tính",
    "range": {
      "A": 362,
      "A+": 361,
      "B": 364,
      "B+": 363,
      "C": 366,
      "C+": 365,
      "D": 368,
      "D+": 367,
      "F": 369
    }
  },
  "2113011": {
    "name": "Toán chuyên đề 1 (Xác suất thống kê)",
    "range": {
      "A": 371,
      "A+": 370,
      "B": 373,
      "B+": 372,
      "C": 375,
      "C+": 374,
      "D": 377,
      "D+": 376,
      "F": 378
    }
  },
  "2113012": {
    "name": "Qui hoạch tuyến tính (Toán chuyên đề 4)",
    "range": {
      "A": 380,
      "A+": 379,
      "B": 382,
      "B+": 381,
      "C": 384,
      "C+": 383,
      "D": 386,
      "D+": 385,
      "F": 387
    }
  },
  "2113018": {
    "name": "Lôgic học",
    "range": {
      "A": 389,
      "A+": 388,
      "B": 391,
      "B+": 390,
      "C": 393,
      "C+": 392,
      "D": 395,
      "D+": 394,
      "F": 396
    }
  },
  "2801806": {
    "name": "Trí tuệ nhân tạo",
    "range": {
      "A": 398,
      "A+": 397,
      "B": 400,
      "B+": 399,
      "C": 402,
      "C+": 401,
      "D": 404,
      "D+": 403,
      "F": 405
    }
  },
  "2801920": {
    "name": "Bài tập lớn học phần 2",
    "range": {
      "A": 407,
      "A+": 406,
      "B": 409,
      "B+": 408,
      "C": 411,
      "C+": 410,
      "D": 413,
      "D+": 412,
      "F": 414
    }
  },
  "2807040": {
    "name": "Quản trị doanh nghiệp",
    "range": {
      "A": 416,
      "A+": 415,
      "B": 418,
      "B+": 417,
      "C": 420,
      "C+": 419,
      "D": 422,
      "D+": 421,
      "F": 423
    }
  },
  "2813010": {
    "name": "Phương pháp tính",
    "range": {
      "A": 425,
      "A+": 424,
      "B": 427,
      "B+": 426,
      "C": 429,
      "C+": 428,
      "D": 431,
      "D+": 430,
      "F": 432
    }
  },
  "2813011": {
    "name": "Xác xuất thống kê",
    "range": {
      "A": 434,
      "A+": 433,
      "B": 436,
      "B+": 435,
      "C": 438,
      "C+": 437,
      "D": 440,
      "D+": 439,
      "F": 441
    }
  }
}